Metadata-Version: 2.1
Name: Tagsnag
Version: 0.10.0
Summary: Search files over multiple Git repos, and extract a certain version
Home-page: https://github.com/beulenyoshi/tagsnag
Author: Thomas Johannesmeyer
Author-email: opensource@geeky.gent
License: Tagsnag
